{"expireTime":9007200878917369000,"key":"f1701feb543f91e156e96dd3c0a5aad0","val":{"name":"IMAGE_PROCESSING","inputPaths":["/Users/toddlambert/Sites/GitHub/UrbanFetish-new/src/img/todd-young1.jpg"],"outputDir":"/Users/toddlambert/Sites/GitHub/UrbanFetish-new/public/static/45fc27052793e34727197c9d79330b15","args":{"isLazy":false,"operations":[{"outputPath":"ad85c/todd-young1.webp","args":{"width":600,"cropFocus":17,"toFormat":"webp","fit":"cover","background":"rgba(0,0,0,1)"}},{"outputPath":"1fb14/todd-young1.webp","args":{"width":960,"cropFocus":17,"toFormat":"webp","fit":"cover","background":"rgba(0,0,0,1)"}}],"pluginOptions":{"base64Width":20,"forceBase64Format":"","useMozJpeg":false,"stripMetadata":true,"lazyImageGeneration":true,"defaultQuality":50,"failOnError":true,"plugins":[]}}}}