{"expireTime":9007200878917369000,"key":"8fd47b01a9455753c31a87d096a1e5df","val":{"name":"IMAGE_PROCESSING","inputPaths":["/Users/toddlambert/Sites/GitHub/UrbanFetish-new/src/img/gallery3/gallery3-abandoned21.jpg"],"outputDir":"/Users/toddlambert/Sites/GitHub/UrbanFetish-new/public/static/c1a03d5de33c5d72ad6d5c86e029034f","args":{"isLazy":false,"operations":[{"outputPath":"ad85c/gallery3-abandoned21.webp","args":{"width":600,"cropFocus":17,"toFormat":"webp","fit":"cover","background":"rgba(0,0,0,1)"}},{"outputPath":"37acb/gallery3-abandoned21.webp","args":{"width":1067,"cropFocus":17,"toFormat":"webp","fit":"cover","background":"rgba(0,0,0,1)"}}],"pluginOptions":{"base64Width":20,"forceBase64Format":"","useMozJpeg":false,"stripMetadata":true,"lazyImageGeneration":true,"defaultQuality":50,"failOnError":true,"plugins":[]}}}}