{"expireTime":9007200878917379000,"key":"cbbecb77247437850120a92b880dd596","val":{"name":"IMAGE_PROCESSING","inputPaths":["/Users/toddlambert/Sites/GitHub/UrbanFetish-new/src/img/gallery3/gallery3-abandoned4.jpg"],"outputDir":"/Users/toddlambert/Sites/GitHub/UrbanFetish-new/public/static/4c0ffec1a85398a052027e6c9de6c22e","args":{"isLazy":false,"operations":[{"outputPath":"f836f/gallery3-abandoned4.jpg","args":{"width":200,"cropFocus":17,"toFormat":"jpg","fit":"cover","background":"rgba(0,0,0,1)"}},{"outputPath":"2244e/gallery3-abandoned4.jpg","args":{"width":400,"cropFocus":17,"toFormat":"jpg","fit":"cover","background":"rgba(0,0,0,1)"}},{"outputPath":"14b42/gallery3-abandoned4.jpg","args":{"width":800,"cropFocus":17,"toFormat":"jpg","fit":"cover","background":"rgba(0,0,0,1)"}},{"outputPath":"81bef/gallery3-abandoned4.jpg","args":{"width":1067,"cropFocus":17,"toFormat":"jpg","fit":"cover","background":"rgba(0,0,0,1)"}}],"pluginOptions":{"base64Width":20,"forceBase64Format":"","useMozJpeg":false,"stripMetadata":true,"lazyImageGeneration":true,"defaultQuality":50,"failOnError":true,"plugins":[]}}}}