{"expireTime":9007200878917369000,"key":"6d04d17782f349218c62707dad446848","val":{"name":"IMAGE_PROCESSING","inputPaths":["/Users/toddlambert/Sites/GitHub/UrbanFetish-new/src/img/industrial/industrial-abandoned3.jpg"],"outputDir":"/Users/toddlambert/Sites/GitHub/UrbanFetish-new/public/static/742885106a510ab55cf709a3b5d0d287","args":{"isLazy":false,"operations":[{"outputPath":"ad85c/industrial-abandoned3.webp","args":{"width":600,"cropFocus":17,"toFormat":"webp","fit":"cover","background":"rgba(0,0,0,1)"}},{"outputPath":"37acb/industrial-abandoned3.webp","args":{"width":1067,"cropFocus":17,"toFormat":"webp","fit":"cover","background":"rgba(0,0,0,1)"}}],"pluginOptions":{"base64Width":20,"forceBase64Format":"","useMozJpeg":false,"stripMetadata":true,"lazyImageGeneration":true,"defaultQuality":50,"failOnError":true,"plugins":[]}}}}